<?xml version="1.0" encoding="UTF-8"?>
<beans xmlns="http://www.springframework.org/schema/beans"
	xmlns:xsi="http://www.w3.org/2001/XMLSchema-instance" 
	xmlns:context="http://www.springframework.org/schema/context"
	xmlns:mvc="http://www.springframework.org/schema/mvc"
	xmlns:util="http://www.springframework.org/schema/util"
	xmlns:aop="http://www.springframework.org/schema/aop"
	xsi:schemaLocation="
	http://www.springframework.org/schema/beans 
	http://www.springframework.org/schema/beans/spring-beans.xsd
	http://www.springframework.org/schema/context 
	http://www.springframework.org/schema/context/spring-context.xsd 
	http://www.springframework.org/schema/util
	http://www.springframework.org/schema/util/spring-util.xsd
	http://www.springframework.org/schema/mvc 
	http://www.springframework.org/schema/mvc/spring-mvc.xsd
	http://www.springframework.org/schema/tx
	http://www.springframework.org/schema/tx/spring-tx.xsd
	http://www.springframework.org/schema/aop
	http://www.springframework.org/schema/aop/spring-aop.xsd">


	<!-- <context:component-scan base-package="com.n.ysb.web" use-default-filters="false">
		<context:include-filter type="annotation" expression="org.springframework.stereotype.Controller" />
	</context:component-scan> -->
	
	<context:component-scan base-package="com.n.ysb.web"></context:component-scan>
	<aop:aspectj-autoproxy />
	
	<!-- 支持上传文件 -->
	<bean id="multipartResolver" class="org.springframework.web.multipart.commons.CommonsMultipartResolver">
		<property name="resolveLazily" value="true" />
		<property name="maxUploadSize" value="524288" /> <!-- in bytes 512K -->
	</bean>

	<bean id="viewResolver" class="org.springframework.web.servlet.view.InternalResourceViewResolver">
		<property name="viewClass" value="org.springframework.web.servlet.view.InternalResourceView" />
		<property name="contentType" value="text/html;charset=utf-8" />
		<property name="prefix" value="/WEB-INF/views/" />
		<property name="suffix" value=".jsp" />
	</bean>

	<bean id="conversionService" class="org.springframework.format.support.FormattingConversionServiceFactoryBean" />
	<mvc:annotation-driven conversion-service="conversionService" validator="validator">
		<mvc:message-converters>
			<bean class="org.springframework.http.converter.StringHttpMessageConverter">
				<constructor-arg value="UTF-8" />
				<property name="writeAcceptCharset" value="false"></property>
			</bean>
			<bean class="org.springframework.http.converter.json.MappingJackson2HttpMessageConverter">
				<property name="objectMapper">
					<bean class="com.fasterxml.jackson.databind.ObjectMapper">
						<property name="dateFormat">
							<bean class="java.text.SimpleDateFormat">
								<constructor-arg type="java.lang.String" value="yyyy-MM-dd HH:mm:ss" />
							</bean>
						</property>
					</bean>
				</property>
			</bean>
		</mvc:message-converters>
	</mvc:annotation-driven>

	<bean id="validator" class="org.springframework.validation.beanvalidation.LocalValidatorFactoryBean">
		<property name="providerClass" value="org.hibernate.validator.HibernateValidator" />
		<property name="validationMessageSource" ref="messageSource" />
	</bean>

	<bean id="messageSource" class="org.springframework.context.support.ReloadableResourceBundleMessageSource">
		<property name="basenames">
			<list>
				<value>classpath:messages</value>
				<value>classpath:org/hibernate/validator/ValidationMessages</value>
			</list>
		</property>
		<property name="useCodeAsDefaultMessage" value="false" />
		<property name="defaultEncoding" value="UTF-8" />
		<property name="cacheSeconds" value="60" />
	</bean>
	
</beans>
